{
  "annotations": {
    "list": [
      {
        "builtIn": 1,
        "datasource": "-- Grafana --",
        "enable": true,
        "hide": true,
        "iconColor": "rgba(0, 211, 255, 1)",
        "name": "Annotations & Alerts",
        "type": "dashboard"
      }
    ]
  },
  "editable": true,
  "gnetId": null,
  "graphTooltip": 0,
  "id": 9,
  "iteration": 1613574010818,
  "links": [],
  "panels": [
    {
      "datasource": "ElasticsearchCOAP",
      "fieldConfig": {
        "defaults": {
          "custom": {
            "align": "center",
            "filterable": false
          },
          "mappings": [],
          "thresholds": {
            "mode": "absolute",
            "steps": [
              {
                "color": "green",
                "value": null
              },
              {
                "color": "red",
                "value": 80
              }
            ]
          },
          "unit": "decbytes"
        },
        "overrides": [
          {
            "matcher": {
              "id": "byName",
              "options": "Count"
            },
            "properties": [
              {
                "id": "displayName",
                "value": "Packets"
              },
              {
                "id": "unit",
                "value": "none"
              }
            ]
          },
          {
            "matcher": {
              "id": "byName",
              "options": "Packet_type.keyword"
            },
            "properties": [
              {
                "id": "displayName",
                "value": "Packet Type"
              },
              {
                "id": "unit",
                "value": "none"
              }
            ]
          },
          {
            "matcher": {
              "id": "byName",
              "options": "Sum"
            },
            "properties": [
              {
                "id": "displayName",
                "value": "Bytes"
              }
            ]
          }
        ]
      },
      "gridPos": {
        "h": 7,
        "w": 10,
        "x": 0,
        "y": 0
      },
      "id": 43,
      "options": {
        "frameIndex": 2,
        "showHeader": true,
        "sortBy": [
          {
            "desc": true,
            "displayName": "Bytes"
          }
        ]
      },
      "pluginVersion": "7.3.4",
      "targets": [
        {
          "bucketAggs": [
            {
              "fake": true,
              "field": "Packet_type.keyword",
              "id": "7",
              "settings": {
                "min_doc_count": 0,
                "order": "desc",
                "orderBy": "_term",
                "size": "10"
              },
              "type": "terms"
            }
          ],
          "metrics": [
            {
              "field": "Bytes",
              "id": "1",
              "meta": {},
              "pipelineVariables": [
                {
                  "name": "var1",
                  "pipelineAgg": "select metric"
                }
              ],
              "settings": {},
              "type": "sum"
            },
            {
              "field": "select field",
              "id": "5",
              "meta": {},
              "settings": {},
              "type": "count"
            }
          ],
          "query": "Packet_type.keyword:$PacketType",
          "refId": "A",
          "timeField": "@timestamp"
        }
      ],
      "timeFrom": null,
      "timeShift": null,
      "title": "Packet Type Stats",
      "type": "table"
    },
    {
      "datasource": "ElasticsearchCOAP",
      "fieldConfig": {
        "defaults": {
          "custom": {
            "align": "center",
            "filterable": false
          },
          "mappings": [],
          "thresholds": {
            "mode": "absolute",
            "steps": [
              {
                "color": "green",
                "value": null
              },
              {
                "color": "red",
                "value": 80
              }
            ]
          }
        },
        "overrides": [
          {
            "matcher": {
              "id": "byName",
              "options": "Uri_host.keyword"
            },
            "properties": [
              {
                "id": "displayName",
                "value": "Uri Host"
              }
            ]
          }
        ]
      },
      "gridPos": {
        "h": 7,
        "w": 4,
        "x": 10,
        "y": 0
      },
      "id": 39,
      "options": {
        "showHeader": true
      },
      "pluginVersion": "7.3.4",
      "targets": [
        {
          "bucketAggs": [
            {
              "field": "Uri_host.keyword",
              "id": "2",
              "settings": {
                "min_doc_count": 0,
                "order": "desc",
                "orderBy": "_term",
                "size": "5"
              },
              "type": "terms"
            }
          ],
          "metrics": [
            {
              "field": "select field",
              "id": "1",
              "type": "count"
            }
          ],
          "refId": "A",
          "timeField": "@timestamp"
        }
      ],
      "timeFrom": null,
      "timeShift": null,
      "title": "Uri Hosts",
      "type": "table"
    },
    {
      "datasource": "ElasticsearchCOAP",
      "fieldConfig": {
        "defaults": {
          "custom": {
            "align": "center",
            "filterable": false
          },
          "mappings": [],
          "thresholds": {
            "mode": "absolute",
            "steps": [
              {
                "color": "green",
                "value": null
              },
              {
                "color": "red",
                "value": 80
              }
            ]
          }
        },
        "overrides": [
          {
            "matcher": {
              "id": "byName",
              "options": "Uri_path.keyword"
            },
            "properties": [
              {
                "id": "displayName",
                "value": "Uri Path"
              }
            ]
          }
        ]
      },
      "gridPos": {
        "h": 7,
        "w": 4,
        "x": 14,
        "y": 0
      },
      "id": 40,
      "options": {
        "showHeader": true
      },
      "pluginVersion": "7.3.4",
      "targets": [
        {
          "bucketAggs": [
            {
              "field": "Uri_path.keyword",
              "id": "2",
              "settings": {
                "min_doc_count": 0,
                "order": "desc",
                "orderBy": "_term",
                "size": "5"
              },
              "type": "terms"
            }
          ],
          "metrics": [
            {
              "field": "select field",
              "id": "1",
              "type": "count"
            }
          ],
          "refId": "A",
          "timeField": "@timestamp"
        }
      ],
      "timeFrom": null,
      "timeShift": null,
      "title": "Uri Paths",
      "type": "table"
    },
    {
      "datasource": "ElasticsearchCOAP",
      "fieldConfig": {
        "defaults": {
          "custom": {},
          "mappings": [],
          "thresholds": {
            "mode": "absolute",
            "steps": [
              {
                "color": "green",
                "value": null
              },
              {
                "color": "red",
                "value": 80
              }
            ]
          },
          "unit": "none"
        },
        "overrides": []
      },
      "gridPos": {
        "h": 3,
        "w": 3,
        "x": 18,
        "y": 0
      },
      "id": 33,
      "options": {
        "colorMode": "value",
        "graphMode": "none",
        "justifyMode": "auto",
        "orientation": "auto",
        "reduceOptions": {
          "calcs": [
            "sum"
          ],
          "fields": "",
          "values": false
        },
        "textMode": "auto"
      },
      "pluginVersion": "7.3.4",
      "targets": [
        {
          "bucketAggs": [
            {
              "field": "@timestamp",
              "id": "2",
              "settings": {
                "interval": "auto",
                "min_doc_count": 0,
                "trimEdges": 0
              },
              "type": "date_histogram"
            }
          ],
          "metrics": [
            {
              "field": "select field",
              "id": "1",
              "type": "count"
            }
          ],
          "refId": "A",
          "timeField": "@timestamp"
        }
      ],
      "timeFrom": null,
      "timeShift": null,
      "title": "Total Packets",
      "type": "stat"
    },
    {
      "datasource": "ElasticsearchCOAP",
      "fieldConfig": {
        "defaults": {
          "custom": {},
          "mappings": [],
          "thresholds": {
            "mode": "absolute",
            "steps": [
              {
                "color": "green",
                "value": null
              },
              {
                "color": "red",
                "value": 80
              }
            ]
          },
          "unit": "decbytes"
        },
        "overrides": []
      },
      "gridPos": {
        "h": 3,
        "w": 3,
        "x": 21,
        "y": 0
      },
      "id": 31,
      "options": {
        "colorMode": "value",
        "graphMode": "none",
        "justifyMode": "auto",
        "orientation": "auto",
        "reduceOptions": {
          "calcs": [
            "sum"
          ],
          "fields": "",
          "values": false
        },
        "textMode": "auto"
      },
      "pluginVersion": "7.3.4",
      "targets": [
        {
          "bucketAggs": [
            {
              "field": "@timestamp",
              "id": "2",
              "settings": {
                "interval": "auto",
                "min_doc_count": 0,
                "trimEdges": 0
              },
              "type": "date_histogram"
            }
          ],
          "metrics": [
            {
              "field": "Bytes",
              "id": "1",
              "meta": {},
              "settings": {},
              "type": "sum"
            }
          ],
          "refId": "A",
          "timeField": "@timestamp"
        }
      ],
      "timeFrom": null,
      "timeShift": null,
      "title": "Total Bytes",
      "type": "stat"
    },
    {
      "cacheTimeout": null,
      "datasource": "ElasticsearchCOAP",
      "fieldConfig": {
        "defaults": {
          "custom": {
            "align": "center",
            "filterable": false
          },
          "mappings": [],
          "thresholds": {
            "mode": "absolute",
            "steps": [
              {
                "color": "green",
                "value": null
              },
              {
                "color": "red",
                "value": 80
              }
            ]
          }
        },
        "overrides": [
          {
            "matcher": {
              "id": "byType",
              "options": "number"
            },
            "properties": [
              {
                "id": "mappings",
                "value": [
                  {
                    "from": "",
                    "id": 1,
                    "text": "Version 1",
                    "to": "",
                    "type": 1,
                    "value": "1"
                  },
                  {
                    "from": "",
                    "id": 2,
                    "text": "Version 2",
                    "to": "",
                    "type": 1,
                    "value": "2"
                  }
                ]
              }
            ]
          }
        ]
      },
      "gridPos": {
        "h": 4,
        "w": 3,
        "x": 18,
        "y": 3
      },
      "id": 35,
      "interval": null,
      "links": [],
      "options": {
        "showHeader": false
      },
      "pluginVersion": "7.3.4",
      "targets": [
        {
          "bucketAggs": [
            {
              "fake": true,
              "field": "Version",
              "id": "3",
              "settings": {
                "min_doc_count": 0,
                "order": "desc",
                "orderBy": "_term",
                "size": "0"
              },
              "type": "terms"
            }
          ],
          "metrics": [
            {
              "field": "Protocol_Name.keyword",
              "id": "1",
              "meta": {},
              "settings": {},
              "type": "count"
            }
          ],
          "refId": "A",
          "timeField": "@timestamp"
        }
      ],
      "timeFrom": null,
      "timeShift": null,
      "title": "CoAP versions",
      "transformations": [
        {
          "id": "filterFieldsByName",
          "options": {
            "include": {
              "names": [
                "Version"
              ]
            }
          }
        }
      ],
      "type": "table"
    },
    {
      "datasource": "ElasticsearchCOAP",
      "fieldConfig": {
        "defaults": {
          "custom": {
            "align": "center",
            "filterable": false
          },
          "mappings": [],
          "thresholds": {
            "mode": "absolute",
            "steps": [
              {
                "color": "green",
                "value": null
              },
              {
                "color": "red",
                "value": 80
              }
            ]
          }
        },
        "overrides": []
      },
      "gridPos": {
        "h": 4,
        "w": 3,
        "x": 21,
        "y": 3
      },
      "id": 37,
      "options": {
        "showHeader": false
      },
      "pluginVersion": "7.3.4",
      "targets": [
        {
          "bucketAggs": [
            {
              "fake": true,
              "field": "Port_src",
              "id": "4",
              "settings": {
                "min_doc_count": "1",
                "order": "desc",
                "orderBy": "_count",
                "size": "10"
              },
              "type": "terms"
            },
            {
              "fake": true,
              "field": "IP_src.keyword",
              "id": "3",
              "settings": {
                "min_doc_count": "1",
                "order": "asc",
                "orderBy": "_count",
                "size": "0"
              },
              "type": "terms"
            }
          ],
          "metrics": [
            {
              "field": "Bytes",
              "id": "1",
              "meta": {},
              "settings": {},
              "type": "count"
            }
          ],
          "query": "Port_src:5683",
          "refId": "A",
          "timeField": "@timestamp"
        }
      ],
      "timeFrom": null,
      "timeShift": null,
      "title": "Server IP",
      "transformations": [
        {
          "id": "filterFieldsByName",
          "options": {
            "include": {
              "names": [
                "IP_src.keyword"
              ]
            }
          }
        }
      ],
      "type": "table"
    },
    {
      "datasource": "ElasticsearchCOAP",
      "fieldConfig": {
        "defaults": {
          "custom": {
            "align": "center",
            "filterable": false
          },
          "mappings": [],
          "thresholds": {
            "mode": "absolute",
            "steps": [
              {
                "color": "green",
                "value": null
              },
              {
                "color": "red",
                "value": 80
              }
            ]
          },
          "unit": "decbytes"
        },
        "overrides": [
          {
            "matcher": {
              "id": "byName",
              "options": "Count"
            },
            "properties": [
              {
                "id": "displayName",
                "value": "Packets"
              },
              {
                "id": "unit",
                "value": "none"
              }
            ]
          },
          {
            "matcher": {
              "id": "byName",
              "options": "Packet_type.keyword"
            },
            "properties": [
              {
                "id": "displayName",
                "value": "Packet Type"
              },
              {
                "id": "unit",
                "value": "none"
              }
            ]
          },
          {
            "matcher": {
              "id": "byName",
              "options": "Sum"
            },
            "properties": [
              {
                "id": "displayName",
                "value": "Bytes"
              }
            ]
          },
          {
            "matcher": {
              "id": "byName",
              "options": "Code.keyword"
            },
            "properties": [
              {
                "id": "displayName",
                "value": "Code"
              }
            ]
          }
        ]
      },
      "gridPos": {
        "h": 8,
        "w": 12,
        "x": 0,
        "y": 7
      },
      "id": 9,
      "options": {
        "frameIndex": 2,
        "showHeader": true,
        "sortBy": [
          {
            "desc": true,
            "displayName": "Bytes"
          }
        ]
      },
      "pluginVersion": "7.3.4",
      "targets": [
        {
          "bucketAggs": [
            {
              "fake": true,
              "field": "Packet_type.keyword",
              "id": "7",
              "settings": {
                "min_doc_count": 0,
                "order": "desc",
                "orderBy": "_term",
                "size": "10"
              },
              "type": "terms"
            },
            {
              "fake": true,
              "field": "Code.keyword",
              "id": "6",
              "settings": {
                "min_doc_count": 0,
                "order": "desc",
                "orderBy": "_term",
                "size": "10"
              },
              "type": "terms"
            }
          ],
          "metrics": [
            {
              "field": "Bytes",
              "id": "1",
              "meta": {},
              "pipelineVariables": [
                {
                  "name": "var1",
                  "pipelineAgg": "select metric"
                }
              ],
              "settings": {},
              "type": "sum"
            },
            {
              "field": "select field",
              "id": "5",
              "meta": {},
              "settings": {},
              "type": "count"
            }
          ],
          "query": "Packet_type.keyword:$PacketType",
          "refId": "A",
          "timeField": "@timestamp"
        }
      ],
      "timeFrom": null,
      "timeShift": null,
      "title": "Packet Type and Code Stats",
      "type": "table"
    },
    {
      "datasource": "ElasticsearchCOAP",
      "fieldConfig": {
        "defaults": {
          "custom": {
            "align": "center",
            "filterable": false
          },
          "mappings": [],
          "thresholds": {
            "mode": "absolute",
            "steps": [
              {
                "color": "green",
                "value": null
              },
              {
                "color": "red",
                "value": 80
              }
            ]
          }
        },
        "overrides": [
          {
            "matcher": {
              "id": "byName",
              "options": "Code.keyword"
            },
            "properties": [
              {
                "id": "displayName",
                "value": "Code"
              }
            ]
          },
          {
            "matcher": {
              "id": "byName",
              "options": "Count"
            },
            "properties": [
              {
                "id": "displayName",
                "value": "Packets"
              }
            ]
          }
        ]
      },
      "gridPos": {
        "h": 8,
        "w": 12,
        "x": 12,
        "y": 7
      },
      "id": 42,
      "options": {
        "showHeader": true
      },
      "pluginVersion": "7.3.4",
      "targets": [
        {
          "bucketAggs": [
            {
              "field": "Code.keyword",
              "id": "2",
              "settings": {
                "min_doc_count": 0,
                "order": "desc",
                "orderBy": "_term",
                "size": "10"
              },
              "type": "terms"
            }
          ],
          "metrics": [
            {
              "field": "select field",
              "id": "1",
              "type": "count"
            }
          ],
          "refId": "A",
          "timeField": "@timestamp"
        }
      ],
      "timeFrom": null,
      "timeShift": null,
      "title": "Code stats",
      "type": "table"
    },
    {
      "aliasColors": {},
      "bars": false,
      "dashLength": 10,
      "dashes": false,
      "datasource": "ElasticsearchCOAP",
      "fieldConfig": {
        "defaults": {
          "custom": {}
        },
        "overrides": [
          {
            "matcher": {
              "id": "byName",
              "options": "Count"
            },
            "properties": [
              {
                "id": "displayName",
                "value": "Packet"
              }
            ]
          }
        ]
      },
      "fill": 1,
      "fillGradient": 0,
      "gridPos": {
        "h": 8,
        "w": 12,
        "x": 0,
        "y": 15
      },
      "hiddenSeries": false,
      "id": 29,
      "legend": {
        "avg": false,
        "current": false,
        "max": false,
        "min": false,
        "show": true,
        "total": false,
        "values": false
      },
      "lines": true,
      "linewidth": 1,
      "nullPointMode": "null",
      "options": {
        "alertThreshold": true
      },
      "percentage": false,
      "pluginVersion": "7.3.4",
      "pointradius": 2,
      "points": false,
      "renderer": "flot",
      "seriesOverrides": [
        {
          "alias": "Sum Bytes",
          "yaxis": 2
        }
      ],
      "spaceLength": 10,
      "stack": false,
      "steppedLine": false,
      "targets": [
        {
          "bucketAggs": [
            {
              "field": "@timestamp",
              "id": "2",
              "settings": {
                "interval": "1s",
                "min_doc_count": 0,
                "trimEdges": 0
              },
              "type": "date_histogram"
            }
          ],
          "metrics": [
            {
              "field": "select field",
              "id": "1",
              "type": "count"
            },
            {
              "field": "Bytes",
              "id": "3",
              "meta": {},
              "settings": {},
              "type": "sum"
            }
          ],
          "refId": "A",
          "timeField": "@timestamp"
        }
      ],
      "thresholds": [],
      "timeFrom": null,
      "timeRegions": [],
      "timeShift": null,
      "title": "Packet - Byte relation",
      "tooltip": {
        "shared": true,
        "sort": 0,
        "value_type": "individual"
      },
      "type": "graph",
      "xaxis": {
        "buckets": null,
        "mode": "time",
        "name": null,
        "show": true,
        "values": []
      },
      "yaxes": [
        {
          "format": "short",
          "label": "Packets",
          "logBase": 1,
          "max": null,
          "min": null,
          "show": true
        },
        {
          "format": "decbytes",
          "label": "Bytes",
          "logBase": 1,
          "max": null,
          "min": null,
          "show": true
        }
      ],
      "yaxis": {
        "align": false,
        "alignLevel": null
      }
    },
    {
      "aliasColors": {},
      "bars": false,
      "dashLength": 10,
      "dashes": false,
      "datasource": "ElasticsearchCOAP",
      "fieldConfig": {
        "defaults": {
          "custom": {}
        },
        "overrides": []
      },
      "fill": 1,
      "fillGradient": 0,
      "gridPos": {
        "h": 8,
        "w": 12,
        "x": 12,
        "y": 15
      },
      "hiddenSeries": false,
      "id": 13,
      "legend": {
        "avg": false,
        "current": false,
        "max": false,
        "min": false,
        "show": true,
        "total": false,
        "values": false
      },
      "lines": true,
      "linewidth": 1,
      "nullPointMode": "null",
      "options": {
        "alertThreshold": true
      },
      "percentage": false,
      "pluginVersion": "7.3.4",
      "pointradius": 2,
      "points": false,
      "renderer": "flot",
      "seriesOverrides": [],
      "spaceLength": 10,
      "stack": false,
      "steppedLine": false,
      "targets": [
        {
          "bucketAggs": [
            {
              "fake": true,
              "field": "Packet_type.keyword",
              "id": "3",
              "settings": {
                "min_doc_count": 0,
                "order": "desc",
                "orderBy": "_term",
                "size": "0"
              },
              "type": "terms"
            },
            {
              "field": "@timestamp",
              "id": "2",
              "settings": {
                "interval": "1s",
                "min_doc_count": 0,
                "trimEdges": 0
              },
              "type": "date_histogram"
            }
          ],
          "metrics": [
            {
              "field": "Bytes",
              "id": "1",
              "meta": {},
              "settings": {},
              "type": "sum"
            }
          ],
          "query": "Packet_type.keyword:$PacketType",
          "refId": "A",
          "timeField": "@timestamp"
        }
      ],
      "thresholds": [],
      "timeFrom": null,
      "timeRegions": [],
      "timeShift": null,
      "title": "Bytes",
      "tooltip": {
        "shared": true,
        "sort": 0,
        "value_type": "individual"
      },
      "type": "graph",
      "xaxis": {
        "buckets": null,
        "mode": "time",
        "name": null,
        "show": true,
        "values": []
      },
      "yaxes": [
        {
          "format": "decbytes",
          "label": "Bytes",
          "logBase": 1,
          "max": null,
          "min": null,
          "show": true
        },
        {
          "format": "short",
          "label": null,
          "logBase": 1,
          "max": null,
          "min": null,
          "show": true
        }
      ],
      "yaxis": {
        "align": false,
        "alignLevel": null
      }
    },
    {
      "datasource": "ElasticsearchCOAP",
      "fieldConfig": {
        "defaults": {
          "custom": {},
          "mappings": [],
          "thresholds": {
            "mode": "absolute",
            "steps": [
              {
                "color": "green",
                "value": null
              },
              {
                "color": "red",
                "value": 80
              }
            ]
          },
          "unit": "s"
        },
        "overrides": []
      },
      "gridPos": {
        "h": 8,
        "w": 12,
        "x": 0,
        "y": 23
      },
      "id": 17,
      "options": {
        "colorMode": "value",
        "graphMode": "area",
        "justifyMode": "auto",
        "orientation": "auto",
        "reduceOptions": {
          "calcs": [
            "mean"
          ],
          "fields": "",
          "values": false
        },
        "textMode": "auto"
      },
      "pluginVersion": "7.3.4",
      "targets": [
        {
          "bucketAggs": [
            {
              "fake": true,
              "field": "IP_src.keyword",
              "id": "3",
              "settings": {
                "min_doc_count": 0,
                "order": "desc",
                "orderBy": "1",
                "size": "0"
              },
              "type": "terms"
            },
            {
              "field": "@timestamp",
              "id": "2",
              "settings": {
                "interval": "1m",
                "min_doc_count": 0,
                "trimEdges": 0
              },
              "type": "date_histogram"
            }
          ],
          "metrics": [
            {
              "field": "RTT",
              "id": "1",
              "meta": {},
              "settings": {},
              "type": "max"
            }
          ],
          "query": "IP_src:$Ip",
          "refId": "A",
          "timeField": "@timestamp"
        }
      ],
      "timeFrom": null,
      "timeShift": null,
      "title": "Maximum Response Time",
      "type": "stat"
    },
    {
      "aliasColors": {},
      "bars": false,
      "dashLength": 10,
      "dashes": false,
      "datasource": "ElasticsearchCOAP",
      "fieldConfig": {
        "defaults": {
          "custom": {},
          "mappings": [],
          "thresholds": {
            "mode": "absolute",
            "steps": [
              {
                "color": "green",
                "value": null
              },
              {
                "color": "red",
                "value": 80
              }
            ]
          }
        },
        "overrides": []
      },
      "fill": 1,
      "fillGradient": 0,
      "gridPos": {
        "h": 8,
        "w": 12,
        "x": 12,
        "y": 23
      },
      "hiddenSeries": false,
      "id": 5,
      "legend": {
        "avg": false,
        "current": false,
        "hideEmpty": false,
        "hideZero": false,
        "max": false,
        "min": false,
        "show": true,
        "total": false,
        "values": false
      },
      "lines": true,
      "linewidth": 1,
      "nullPointMode": "null",
      "options": {
        "alertThreshold": true
      },
      "percentage": false,
      "pluginVersion": "7.3.4",
      "pointradius": 1,
      "points": true,
      "renderer": "flot",
      "seriesOverrides": [],
      "spaceLength": 10,
      "stack": false,
      "steppedLine": false,
      "targets": [
        {
          "bucketAggs": [
            {
              "fake": true,
              "field": "IP_src.keyword",
              "id": "3",
              "settings": {
                "min_doc_count": 0,
                "order": "desc",
                "orderBy": "_term",
                "size": "0"
              },
              "type": "terms"
            },
            {
              "field": "@timestamp",
              "id": "2",
              "settings": {
                "interval": "10s",
                "min_doc_count": 0,
                "trimEdges": 0
              },
              "type": "date_histogram"
            }
          ],
          "metrics": [
            {
              "field": "RTT",
              "id": "1",
              "meta": {
                "std_deviation": true,
                "std_deviation_bounds_lower": false,
                "std_deviation_bounds_upper": false
              },
              "settings": {},
              "type": "extended_stats"
            }
          ],
          "query": "IP_src.keyword:$Ip",
          "refId": "A",
          "timeField": "@timestamp"
        }
      ],
      "thresholds": [],
      "timeFrom": null,
      "timeRegions": [],
      "timeShift": null,
      "title": "Response time ",
      "tooltip": {
        "shared": true,
        "sort": 0,
        "value_type": "individual"
      },
      "type": "graph",
      "xaxis": {
        "buckets": null,
        "mode": "time",
        "name": null,
        "show": true,
        "values": []
      },
      "yaxes": [
        {
          "format": "s",
          "label": "seconds",
          "logBase": 1,
          "max": null,
          "min": null,
          "show": true
        },
        {
          "format": "short",
          "label": null,
          "logBase": 1,
          "max": null,
          "min": null,
          "show": true
        }
      ],
      "yaxis": {
        "align": false,
        "alignLevel": null
      }
    },
    {
      "aliasColors": {},
      "bars": false,
      "dashLength": 10,
      "dashes": false,
      "datasource": "ElasticsearchCOAP",
      "fieldConfig": {
        "defaults": {
          "custom": {}
        },
        "overrides": []
      },
      "fill": 1,
      "fillGradient": 0,
      "gridPos": {
        "h": 8,
        "w": 12,
        "x": 0,
        "y": 31
      },
      "hiddenSeries": false,
      "id": 15,
      "legend": {
        "avg": false,
        "current": false,
        "max": false,
        "min": false,
        "show": true,
        "total": false,
        "values": false
      },
      "lines": true,
      "linewidth": 1,
      "nullPointMode": "null",
      "options": {
        "alertThreshold": true
      },
      "percentage": false,
      "pluginVersion": "7.3.4",
      "pointradius": 2,
      "points": false,
      "renderer": "flot",
      "seriesOverrides": [],
      "spaceLength": 10,
      "stack": false,
      "steppedLine": false,
      "targets": [
        {
          "bucketAggs": [
            {
              "field": "@timestamp",
              "id": "2",
              "settings": {
                "interval": "10s",
                "min_doc_count": 0,
                "trimEdges": 0
              },
              "type": "date_histogram"
            }
          ],
          "metrics": [
            {
              "field": "Bytes",
              "id": "1",
              "meta": {},
              "settings": {},
              "type": "sum"
            }
          ],
          "query": "Port_src:5683",
          "refId": "A",
          "timeField": "@timestamp"
        }
      ],
      "thresholds": [],
      "timeFrom": null,
      "timeRegions": [],
      "timeShift": null,
      "title": "Traffic from servers",
      "tooltip": {
        "shared": true,
        "sort": 0,
        "value_type": "individual"
      },
      "type": "graph",
      "xaxis": {
        "buckets": null,
        "mode": "time",
        "name": null,
        "show": true,
        "values": []
      },
      "yaxes": [
        {
          "decimals": null,
          "format": "decbytes",
          "label": "Bytes",
          "logBase": 1,
          "max": null,
          "min": null,
          "show": true
        },
        {
          "format": "short",
          "label": null,
          "logBase": 1,
          "max": null,
          "min": null,
          "show": true
        }
      ],
      "yaxis": {
        "align": false,
        "alignLevel": null
      }
    },
    {
      "aliasColors": {},
      "bars": false,
      "dashLength": 10,
      "dashes": false,
      "datasource": "ElasticsearchCOAP",
      "fieldConfig": {
        "defaults": {
          "custom": {}
        },
        "overrides": []
      },
      "fill": 1,
      "fillGradient": 0,
      "gridPos": {
        "h": 8,
        "w": 12,
        "x": 12,
        "y": 31
      },
      "hiddenSeries": false,
      "id": 19,
      "legend": {
        "avg": false,
        "current": false,
        "hideEmpty": true,
        "hideZero": true,
        "max": false,
        "min": false,
        "show": true,
        "total": false,
        "values": false
      },
      "lines": true,
      "linewidth": 1,
      "nullPointMode": "null",
      "options": {
        "alertThreshold": true
      },
      "percentage": false,
      "pluginVersion": "7.3.4",
      "pointradius": 2,
      "points": false,
      "renderer": "flot",
      "seriesOverrides": [],
      "spaceLength": 10,
      "stack": false,
      "steppedLine": false,
      "targets": [
        {
          "bucketAggs": [
            {
              "fake": true,
              "field": "IP_src.keyword",
              "id": "3",
              "settings": {
                "min_doc_count": 0,
                "order": "desc",
                "orderBy": "_term",
                "size": "0"
              },
              "type": "terms"
            },
            {
              "field": "@timestamp",
              "id": "2",
              "settings": {
                "interval": "10s",
                "min_doc_count": 0,
                "trimEdges": 0
              },
              "type": "date_histogram"
            }
          ],
          "metrics": [
            {
              "field": "Bytes",
              "id": "1",
              "meta": {},
              "settings": {},
              "type": "sum"
            }
          ],
          "query": "IP_src:$Ip && Port_dst:5683",
          "refId": "A",
          "timeField": "@timestamp"
        }
      ],
      "thresholds": [],
      "timeFrom": null,
      "timeRegions": [],
      "timeShift": null,
      "title": "Client IP traffic",
      "tooltip": {
        "shared": true,
        "sort": 0,
        "value_type": "individual"
      },
      "type": "graph",
      "xaxis": {
        "buckets": null,
        "mode": "time",
        "name": null,
        "show": true,
        "values": []
      },
      "yaxes": [
        {
          "format": "short",
          "label": "Bytes",
          "logBase": 1,
          "max": null,
          "min": null,
          "show": true
        },
        {
          "format": "short",
          "label": null,
          "logBase": 1,
          "max": null,
          "min": null,
          "show": true
        }
      ],
      "yaxis": {
        "align": false,
        "alignLevel": null
      }
    },
    {
      "datasource": "ElasticsearchCOAP",
      "fieldConfig": {
        "defaults": {
          "custom": {},
          "mappings": [],
          "thresholds": {
            "mode": "absolute",
            "steps": [
              {
                "color": "green",
                "value": null
              },
              {
                "color": "red",
                "value": 80
              }
            ]
          }
        },
        "overrides": []
      },
      "gridPos": {
        "h": 3,
        "w": 6,
        "x": 0,
        "y": 39
      },
      "id": 21,
      "options": {
        "colorMode": "value",
        "graphMode": "none",
        "justifyMode": "auto",
        "orientation": "auto",
        "reduceOptions": {
          "calcs": [
            "sum"
          ],
          "fields": "",
          "values": false
        },
        "textMode": "auto"
      },
      "pluginVersion": "7.3.4",
      "targets": [
        {
          "bucketAggs": [
            {
              "field": "@timestamp",
              "id": "2",
              "settings": {
                "interval": "auto",
                "min_doc_count": 0,
                "trimEdges": 0
              },
              "type": "date_histogram"
            }
          ],
          "metrics": [
            {
              "field": "select field",
              "id": "1",
              "type": "count"
            }
          ],
          "query": "Port_dst:5683",
          "refId": "A",
          "timeField": "@timestamp"
        }
      ],
      "timeFrom": null,
      "timeShift": null,
      "title": "Packets to server (port 1883)",
      "type": "stat"
    },
    {
      "datasource": "ElasticsearchCOAP",
      "fieldConfig": {
        "defaults": {
          "custom": {},
          "mappings": [],
          "thresholds": {
            "mode": "absolute",
            "steps": [
              {
                "color": "green",
                "value": null
              },
              {
                "color": "red",
                "value": 80
              }
            ]
          },
          "unit": "decbytes"
        },
        "overrides": []
      },
      "gridPos": {
        "h": 3,
        "w": 6,
        "x": 6,
        "y": 39
      },
      "id": 22,
      "options": {
        "colorMode": "value",
        "graphMode": "none",
        "justifyMode": "auto",
        "orientation": "auto",
        "reduceOptions": {
          "calcs": [
            "sum"
          ],
          "fields": "",
          "values": false
        },
        "textMode": "auto"
      },
      "pluginVersion": "7.3.4",
      "targets": [
        {
          "bucketAggs": [
            {
              "field": "@timestamp",
              "id": "2",
              "settings": {
                "interval": "auto",
                "min_doc_count": 0,
                "trimEdges": 0
              },
              "type": "date_histogram"
            }
          ],
          "metrics": [
            {
              "field": "Bytes",
              "id": "1",
              "meta": {},
              "settings": {},
              "type": "sum"
            }
          ],
          "query": "Port_dst:5683",
          "refId": "A",
          "timeField": "@timestamp"
        }
      ],
      "timeFrom": null,
      "timeShift": null,
      "title": "Total Bytes to broker (port 1883)",
      "type": "stat"
    },
    {
      "datasource": "ElasticsearchCOAP",
      "fieldConfig": {
        "defaults": {
          "custom": {},
          "mappings": [],
          "thresholds": {
            "mode": "absolute",
            "steps": [
              {
                "color": "green",
                "value": null
              },
              {
                "color": "red",
                "value": 80
              }
            ]
          },
          "unit": "none"
        },
        "overrides": []
      },
      "gridPos": {
        "h": 3,
        "w": 6,
        "x": 12,
        "y": 39
      },
      "id": 23,
      "options": {
        "colorMode": "value",
        "graphMode": "none",
        "justifyMode": "auto",
        "orientation": "auto",
        "reduceOptions": {
          "calcs": [
            "sum"
          ],
          "fields": "",
          "values": false
        },
        "textMode": "auto"
      },
      "pluginVersion": "7.3.4",
      "targets": [
        {
          "bucketAggs": [
            {
              "field": "@timestamp",
              "id": "2",
              "settings": {
                "interval": "auto",
                "min_doc_count": 0,
                "trimEdges": 0
              },
              "type": "date_histogram"
            }
          ],
          "metrics": [
            {
              "field": "Bytes",
              "id": "1",
              "meta": {},
              "settings": {},
              "type": "count"
            }
          ],
          "query": "Port_src:5683",
          "refId": "A",
          "timeField": "@timestamp"
        }
      ],
      "timeFrom": null,
      "timeShift": null,
      "title": "Packets from broker (port 1883)",
      "type": "stat"
    },
    {
      "datasource": "ElasticsearchCOAP",
      "fieldConfig": {
        "defaults": {
          "custom": {},
          "mappings": [],
          "thresholds": {
            "mode": "absolute",
            "steps": [
              {
                "color": "green",
                "value": null
              },
              {
                "color": "red",
                "value": 80
              }
            ]
          },
          "unit": "decbytes"
        },
        "overrides": []
      },
      "gridPos": {
        "h": 3,
        "w": 6,
        "x": 18,
        "y": 39
      },
      "id": 24,
      "options": {
        "colorMode": "value",
        "graphMode": "none",
        "justifyMode": "auto",
        "orientation": "auto",
        "reduceOptions": {
          "calcs": [
            "sum"
          ],
          "fields": "",
          "values": false
        },
        "textMode": "auto"
      },
      "pluginVersion": "7.3.4",
      "targets": [
        {
          "bucketAggs": [
            {
              "field": "@timestamp",
              "id": "2",
              "settings": {
                "interval": "auto",
                "min_doc_count": 0,
                "trimEdges": 0
              },
              "type": "date_histogram"
            }
          ],
          "metrics": [
            {
              "field": "Bytes",
              "id": "1",
              "meta": {},
              "settings": {},
              "type": "sum"
            }
          ],
          "query": "Port_src:5683",
          "refId": "A",
          "timeField": "@timestamp"
        }
      ],
      "timeFrom": null,
      "timeShift": null,
      "title": "Total Bytes from broker (port 1883)",
      "type": "stat"
    },
    {
      "aliasColors": {},
      "bars": false,
      "dashLength": 10,
      "dashes": false,
      "datasource": "ElasticsearchCOAP",
      "fieldConfig": {
        "defaults": {
          "custom": {}
        },
        "overrides": []
      },
      "fill": 1,
      "fillGradient": 0,
      "gridPos": {
        "h": 8,
        "w": 12,
        "x": 0,
        "y": 42
      },
      "hiddenSeries": false,
      "id": 26,
      "legend": {
        "avg": false,
        "current": false,
        "hideEmpty": true,
        "hideZero": true,
        "max": false,
        "min": false,
        "show": true,
        "total": false,
        "values": false
      },
      "lines": true,
      "linewidth": 1,
      "nullPointMode": "null",
      "options": {
        "alertThreshold": true
      },
      "percentage": false,
      "pluginVersion": "7.3.4",
      "pointradius": 2,
      "points": false,
      "renderer": "flot",
      "seriesOverrides": [],
      "spaceLength": 10,
      "stack": false,
      "steppedLine": false,
      "targets": [
        {
          "bucketAggs": [
            {
              "fake": true,
              "field": "Packet_type.keyword",
              "id": "3",
              "settings": {
                "min_doc_count": 0,
                "order": "desc",
                "orderBy": "_term",
                "size": "10"
              },
              "type": "terms"
            },
            {
              "field": "@timestamp",
              "id": "2",
              "settings": {
                "interval": "auto",
                "min_doc_count": 0,
                "trimEdges": 0
              },
              "type": "date_histogram"
            }
          ],
          "metrics": [
            {
              "field": "Bytes",
              "id": "1",
              "meta": {},
              "settings": {},
              "type": "sum"
            }
          ],
          "query": "Port_dst:5683 &&  Packet_type:$PacketType",
          "refId": "A",
          "timeField": "@timestamp"
        }
      ],
      "thresholds": [],
      "timeFrom": null,
      "timeRegions": [],
      "timeShift": null,
      "title": "Bytes to broker (port 1883)",
      "tooltip": {
        "shared": true,
        "sort": 0,
        "value_type": "individual"
      },
      "type": "graph",
      "xaxis": {
        "buckets": null,
        "mode": "time",
        "name": null,
        "show": true,
        "values": []
      },
      "yaxes": [
        {
          "format": "decbytes",
          "label": "Bytes",
          "logBase": 1,
          "max": null,
          "min": null,
          "show": true
        },
        {
          "format": "short",
          "label": null,
          "logBase": 1,
          "max": null,
          "min": null,
          "show": true
        }
      ],
      "yaxis": {
        "align": false,
        "alignLevel": null
      }
    },
    {
      "aliasColors": {},
      "bars": false,
      "dashLength": 10,
      "dashes": false,
      "datasource": "ElasticsearchCOAP",
      "fieldConfig": {
        "defaults": {
          "custom": {}
        },
        "overrides": []
      },
      "fill": 1,
      "fillGradient": 0,
      "gridPos": {
        "h": 8,
        "w": 12,
        "x": 12,
        "y": 42
      },
      "hiddenSeries": false,
      "id": 27,
      "legend": {
        "avg": false,
        "current": false,
        "hideEmpty": true,
        "hideZero": true,
        "max": false,
        "min": false,
        "show": true,
        "total": false,
        "values": false
      },
      "lines": true,
      "linewidth": 1,
      "nullPointMode": "null",
      "options": {
        "alertThreshold": true
      },
      "percentage": false,
      "pluginVersion": "7.3.4",
      "pointradius": 2,
      "points": false,
      "renderer": "flot",
      "seriesOverrides": [],
      "spaceLength": 10,
      "stack": false,
      "steppedLine": false,
      "targets": [
        {
          "bucketAggs": [
            {
              "fake": true,
              "field": "Packet_type.keyword",
              "id": "3",
              "settings": {
                "min_doc_count": 0,
                "order": "desc",
                "orderBy": "_term",
                "size": "10"
              },
              "type": "terms"
            },
            {
              "field": "@timestamp",
              "id": "2",
              "settings": {
                "interval": "auto",
                "min_doc_count": 0,
                "trimEdges": 0
              },
              "type": "date_histogram"
            }
          ],
          "metrics": [
            {
              "field": "Bytes",
              "id": "1",
              "meta": {},
              "settings": {},
              "type": "sum"
            }
          ],
          "query": "Port_src:5683 &&  Packet_type:$PacketType",
          "refId": "A",
          "timeField": "@timestamp"
        }
      ],
      "thresholds": [],
      "timeFrom": null,
      "timeRegions": [],
      "timeShift": null,
      "title": "Bytes from broker (port 1883)",
      "tooltip": {
        "shared": true,
        "sort": 0,
        "value_type": "individual"
      },
      "type": "graph",
      "xaxis": {
        "buckets": null,
        "mode": "time",
        "name": null,
        "show": true,
        "values": []
      },
      "yaxes": [
        {
          "format": "decbytes",
          "label": "Bytes",
          "logBase": 1,
          "max": null,
          "min": null,
          "show": true
        },
        {
          "format": "short",
          "label": null,
          "logBase": 1,
          "max": null,
          "min": null,
          "show": true
        }
      ],
      "yaxis": {
        "align": false,
        "alignLevel": null
      }
    },
    {
      "aliasColors": {},
      "bars": false,
      "dashLength": 10,
      "dashes": false,
      "datasource": "ElasticsearchCOAP",
      "description": "",
      "fieldConfig": {
        "defaults": {
          "custom": {}
        },
        "overrides": []
      },
      "fill": 1,
      "fillGradient": 0,
      "gridPos": {
        "h": 8,
        "w": 12,
        "x": 0,
        "y": 50
      },
      "hiddenSeries": false,
      "id": 2,
      "legend": {
        "avg": false,
        "current": false,
        "hideEmpty": true,
        "hideZero": true,
        "max": false,
        "min": false,
        "show": true,
        "total": false,
        "values": false
      },
      "lines": true,
      "linewidth": 1,
      "nullPointMode": "null",
      "options": {
        "alertThreshold": true
      },
      "percentage": false,
      "pluginVersion": "7.3.4",
      "pointradius": 2,
      "points": false,
      "renderer": "flot",
      "seriesOverrides": [],
      "spaceLength": 10,
      "stack": false,
      "steppedLine": false,
      "targets": [
        {
          "bucketAggs": [
            {
              "fake": true,
              "field": "IP_src.keyword",
              "id": "3",
              "settings": {
                "min_doc_count": 0,
                "order": "desc",
                "orderBy": "_term",
                "size": "0"
              },
              "type": "terms"
            },
            {
              "field": "@timestamp",
              "id": "2",
              "settings": {
                "interval": "1s",
                "min_doc_count": 0,
                "trimEdges": 0
              },
              "type": "date_histogram"
            }
          ],
          "metrics": [
            {
              "field": "Bytes",
              "id": "1",
              "meta": {},
              "settings": {},
              "type": "sum"
            }
          ],
          "query": "IP_src.keyword:$Ip",
          "refId": "A",
          "timeField": "@timestamp"
        }
      ],
      "thresholds": [],
      "timeFrom": null,
      "timeRegions": [],
      "timeShift": null,
      "title": "Sent Bytes",
      "tooltip": {
        "shared": true,
        "sort": 0,
        "value_type": "individual"
      },
      "type": "graph",
      "xaxis": {
        "buckets": null,
        "mode": "time",
        "name": null,
        "show": true,
        "values": []
      },
      "yaxes": [
        {
          "format": "decbytes",
          "label": "Bytes",
          "logBase": 1,
          "max": null,
          "min": null,
          "show": true
        },
        {
          "format": "short",
          "label": null,
          "logBase": 1,
          "max": null,
          "min": null,
          "show": false
        }
      ],
      "yaxis": {
        "align": false,
        "alignLevel": null
      }
    },
    {
      "aliasColors": {},
      "bars": false,
      "dashLength": 10,
      "dashes": false,
      "datasource": "ElasticsearchCOAP",
      "description": "",
      "fieldConfig": {
        "defaults": {
          "custom": {}
        },
        "overrides": []
      },
      "fill": 1,
      "fillGradient": 0,
      "gridPos": {
        "h": 8,
        "w": 12,
        "x": 12,
        "y": 50
      },
      "hiddenSeries": false,
      "id": 3,
      "legend": {
        "avg": false,
        "current": false,
        "hideEmpty": true,
        "hideZero": true,
        "max": false,
        "min": false,
        "show": true,
        "total": false,
        "values": false
      },
      "lines": true,
      "linewidth": 1,
      "nullPointMode": "null",
      "options": {
        "alertThreshold": true
      },
      "percentage": false,
      "pluginVersion": "7.3.4",
      "pointradius": 2,
      "points": false,
      "renderer": "flot",
      "seriesOverrides": [],
      "spaceLength": 10,
      "stack": false,
      "steppedLine": false,
      "targets": [
        {
          "bucketAggs": [
            {
              "fake": true,
              "field": "IP_dst.keyword",
              "id": "3",
              "settings": {
                "min_doc_count": 0,
                "order": "desc",
                "orderBy": "_term",
                "size": "0"
              },
              "type": "terms"
            },
            {
              "field": "@timestamp",
              "id": "2",
              "settings": {
                "interval": "auto",
                "min_doc_count": 0,
                "trimEdges": 0
              },
              "type": "date_histogram"
            }
          ],
          "metrics": [
            {
              "field": "Bytes",
              "id": "1",
              "meta": {},
              "settings": {},
              "type": "sum"
            }
          ],
          "query": "IP_dst.keyword:$Ip",
          "refId": "A",
          "timeField": "@timestamp"
        }
      ],
      "thresholds": [],
      "timeFrom": null,
      "timeRegions": [],
      "timeShift": null,
      "title": "Received Bytes",
      "tooltip": {
        "shared": true,
        "sort": 0,
        "value_type": "individual"
      },
      "type": "graph",
      "xaxis": {
        "buckets": null,
        "mode": "time",
        "name": null,
        "show": true,
        "values": []
      },
      "yaxes": [
        {
          "format": "decbytes",
          "label": "Bytes",
          "logBase": 1,
          "max": null,
          "min": null,
          "show": true
        },
        {
          "format": "short",
          "label": null,
          "logBase": 1,
          "max": null,
          "min": null,
          "show": false
        }
      ],
      "yaxis": {
        "align": false,
        "alignLevel": null
      }
    },
    {
      "aliasColors": {},
      "bars": false,
      "dashLength": 10,
      "dashes": false,
      "datasource": "ElasticsearchCOAP",
      "description": "",
      "fieldConfig": {
        "defaults": {
          "custom": {}
        },
        "overrides": []
      },
      "fill": 1,
      "fillGradient": 0,
      "gridPos": {
        "h": 8,
        "w": 12,
        "x": 0,
        "y": 58
      },
      "hiddenSeries": false,
      "id": 6,
      "legend": {
        "avg": false,
        "current": false,
        "hideEmpty": true,
        "hideZero": true,
        "max": false,
        "min": false,
        "show": true,
        "total": false,
        "values": false
      },
      "lines": true,
      "linewidth": 1,
      "nullPointMode": "null",
      "options": {
        "alertThreshold": true
      },
      "percentage": false,
      "pluginVersion": "7.3.4",
      "pointradius": 2,
      "points": false,
      "renderer": "flot",
      "seriesOverrides": [],
      "spaceLength": 10,
      "stack": false,
      "steppedLine": false,
      "targets": [
        {
          "bucketAggs": [
            {
              "fake": true,
              "field": "IP_src.keyword",
              "id": "3",
              "settings": {
                "min_doc_count": 0,
                "order": "desc",
                "orderBy": "1",
                "size": "5"
              },
              "type": "terms"
            },
            {
              "field": "@timestamp",
              "id": "2",
              "settings": {
                "interval": "auto",
                "min_doc_count": 0,
                "trimEdges": 0
              },
              "type": "date_histogram"
            }
          ],
          "metrics": [
            {
              "field": "Bytes",
              "id": "1",
              "meta": {},
              "settings": {},
              "type": "sum"
            }
          ],
          "query": "IP_src.keyword:$Ip && IP_dst.keyword:$Ip",
          "refId": "A",
          "timeField": "@timestamp"
        }
      ],
      "thresholds": [],
      "timeFrom": null,
      "timeRegions": [],
      "timeShift": null,
      "title": "Sent Bytes (Top 5)",
      "tooltip": {
        "shared": true,
        "sort": 0,
        "value_type": "individual"
      },
      "type": "graph",
      "xaxis": {
        "buckets": null,
        "mode": "time",
        "name": null,
        "show": true,
        "values": []
      },
      "yaxes": [
        {
          "format": "decbytes",
          "label": "Bytes",
          "logBase": 1,
          "max": null,
          "min": null,
          "show": true
        },
        {
          "format": "short",
          "label": null,
          "logBase": 1,
          "max": null,
          "min": null,
          "show": false
        }
      ],
      "yaxis": {
        "align": false,
        "alignLevel": null
      }
    },
    {
      "aliasColors": {},
      "bars": false,
      "dashLength": 10,
      "dashes": false,
      "datasource": "ElasticsearchCOAP",
      "description": "",
      "fieldConfig": {
        "defaults": {
          "custom": {}
        },
        "overrides": []
      },
      "fill": 1,
      "fillGradient": 0,
      "gridPos": {
        "h": 8,
        "w": 12,
        "x": 12,
        "y": 58
      },
      "hiddenSeries": false,
      "id": 7,
      "legend": {
        "avg": false,
        "current": false,
        "hideEmpty": true,
        "hideZero": true,
        "max": false,
        "min": false,
        "show": true,
        "total": false,
        "values": false
      },
      "lines": true,
      "linewidth": 1,
      "nullPointMode": "null",
      "options": {
        "alertThreshold": true
      },
      "percentage": false,
      "pluginVersion": "7.3.4",
      "pointradius": 2,
      "points": false,
      "renderer": "flot",
      "seriesOverrides": [],
      "spaceLength": 10,
      "stack": false,
      "steppedLine": false,
      "targets": [
        {
          "bucketAggs": [
            {
              "fake": true,
              "field": "IP_dst.keyword",
              "id": "3",
              "settings": {
                "min_doc_count": 0,
                "order": "desc",
                "orderBy": "1",
                "size": "5"
              },
              "type": "terms"
            },
            {
              "field": "@timestamp",
              "id": "2",
              "settings": {
                "interval": "auto",
                "min_doc_count": 0,
                "trimEdges": 0
              },
              "type": "date_histogram"
            }
          ],
          "metrics": [
            {
              "field": "Bytes",
              "id": "1",
              "meta": {},
              "settings": {},
              "type": "sum"
            }
          ],
          "query": "IP_dst.keyword:$Ip",
          "refId": "A",
          "timeField": "@timestamp"
        }
      ],
      "thresholds": [],
      "timeFrom": null,
      "timeRegions": [],
      "timeShift": null,
      "title": "Receive Bytes (Top 5)",
      "tooltip": {
        "shared": true,
        "sort": 0,
        "value_type": "individual"
      },
      "type": "graph",
      "xaxis": {
        "buckets": null,
        "mode": "time",
        "name": null,
        "show": true,
        "values": []
      },
      "yaxes": [
        {
          "format": "decbytes",
          "label": "Bytes",
          "logBase": 1,
          "max": null,
          "min": null,
          "show": true
        },
        {
          "format": "short",
          "label": null,
          "logBase": 1,
          "max": null,
          "min": null,
          "show": false
        }
      ],
      "yaxis": {
        "align": false,
        "alignLevel": null
      }
    },
    {
      "aliasColors": {},
      "bars": false,
      "dashLength": 10,
      "dashes": false,
      "datasource": "Elasticsearch",
      "fieldConfig": {
        "defaults": {
          "custom": {}
        },
        "overrides": [
          {
            "matcher": {
              "id": "byName",
              "options": "1883"
            },
            "properties": [
              {
                "id": "displayName",
                "value": "MQTT"
              }
            ]
          }
        ]
      },
      "fill": 1,
      "fillGradient": 0,
      "gridPos": {
        "h": 8,
        "w": 12,
        "x": 0,
        "y": 66
      },
      "hiddenSeries": false,
      "id": 11,
      "legend": {
        "avg": false,
        "current": false,
        "max": false,
        "min": false,
        "show": true,
        "total": false,
        "values": false
      },
      "lines": true,
      "linewidth": 1,
      "nullPointMode": "null",
      "options": {
        "alertThreshold": true
      },
      "percentage": false,
      "pluginVersion": "7.3.4",
      "pointradius": 2,
      "points": false,
      "renderer": "flot",
      "seriesOverrides": [],
      "spaceLength": 10,
      "stack": false,
      "steppedLine": false,
      "targets": [
        {
          "bucketAggs": [
            {
              "fake": true,
              "field": "Port_src",
              "id": "3",
              "settings": {
                "min_doc_count": 0,
                "order": "desc",
                "orderBy": "1",
                "size": "10"
              },
              "type": "terms"
            },
            {
              "field": "@timestamp",
              "id": "2",
              "settings": {
                "interval": "1s",
                "min_doc_count": 0,
                "trimEdges": 0
              },
              "type": "date_histogram"
            }
          ],
          "hide": false,
          "metrics": [
            {
              "field": "Bytes",
              "id": "1",
              "meta": {},
              "settings": {},
              "type": "sum"
            }
          ],
          "query": "",
          "refId": "A",
          "timeField": "@timestamp"
        }
      ],
      "thresholds": [],
      "timeFrom": null,
      "timeRegions": [],
      "timeShift": null,
      "title": "Panel Title",
      "tooltip": {
        "shared": true,
        "sort": 0,
        "value_type": "individual"
      },
      "type": "graph",
      "xaxis": {
        "buckets": null,
        "mode": "time",
        "name": null,
        "show": true,
        "values": []
      },
      "yaxes": [
        {
          "format": "short",
          "label": null,
          "logBase": 1,
          "max": null,
          "min": null,
          "show": true
        },
        {
          "format": "short",
          "label": null,
          "logBase": 1,
          "max": null,
          "min": null,
          "show": true
        }
      ],
      "yaxis": {
        "align": false,
        "alignLevel": null
      }
    }
  ],
  "refresh": false,
  "schemaVersion": 26,
  "style": "dark",
  "tags": [],
  "templating": {
    "list": [
      {
        "allValue": null,
        "current": {
          "selected": true,
          "text": [
            "All"
          ],
          "value": [
            "$__all"
          ]
        },
        "datasource": "ElasticsearchCOAP",
        "definition": "{\"find\": \"terms\", \"field\": \"IP_src.keyword\"}",
        "error": null,
        "hide": 0,
        "includeAll": true,
        "label": "Ip",
        "multi": true,
        "name": "Ip",
        "options": [
          {
            "selected": true,
            "text": "All",
            "value": "$__all"
          },
          {
            "selected": false,
            "text": "192.168.165.65",
            "value": "192.168.165.65"
          },
          {
            "selected": false,
            "text": "192.168.165.66",
            "value": "192.168.165.66"
          },
          {
            "selected": false,
            "text": "203.253.250.32",
            "value": "203.253.250.32"
          }
        ],
        "query": "{\"find\": \"terms\", \"field\": \"IP_src.keyword\"}",
        "refresh": 0,
        "regex": "",
        "skipUrlSync": false,
        "sort": 0,
        "tagValuesQuery": "",
        "tags": [],
        "tagsQuery": "",
        "type": "query",
        "useTags": false
      },
      {
        "allValue": null,
        "current": {
          "selected": true,
          "text": [
            "All"
          ],
          "value": [
            "$__all"
          ]
        },
        "datasource": "ElasticsearchCOAP",
        "definition": "{\"find\": \"terms\", \"field\": \"Port_src\", \"size\":100000}",
        "error": null,
        "hide": 0,
        "includeAll": true,
        "label": "Source Port",
        "multi": true,
        "name": "PortSrc",
        "options": [
          {
            "selected": true,
            "text": "All",
            "value": "$__all"
          },
          {
            "selected": false,
            "text": "5683",
            "value": "5683"
          },
          {
            "selected": false,
            "text": "15684",
            "value": "15684"
          },
          {
            "selected": false,
            "text": "50697",
            "value": "50697"
          }
        ],
        "query": "{\"find\": \"terms\", \"field\": \"Port_src\", \"size\":100000}",
        "refresh": 0,
        "regex": "",
        "skipUrlSync": false,
        "sort": 0,
        "tagValuesQuery": "",
        "tags": [],
        "tagsQuery": "",
        "type": "query",
        "useTags": false
      },
      {
        "allValue": null,
        "current": {
          "selected": true,
          "text": [
            "All"
          ],
          "value": [
            "$__all"
          ]
        },
        "datasource": "ElasticsearchCOAP",
        "definition": "{\"find\": \"terms\", \"field\": \"Packet_type.keyword\"}",
        "error": null,
        "hide": 0,
        "includeAll": true,
        "label": "Packet type",
        "multi": true,
        "name": "PacketType",
        "options": [
          {
            "selected": true,
            "text": "All",
            "value": "$__all"
          },
          {
            "selected": false,
            "text": "AKNOWLEDGEMENT",
            "value": "AKNOWLEDGEMENT"
          },
          {
            "selected": false,
            "text": "CONFIRMABLE",
            "value": "CONFIRMABLE"
          }
        ],
        "query": "{\"find\": \"terms\", \"field\": \"Packet_type.keyword\"}",
        "refresh": 0,
        "regex": "",
        "skipUrlSync": false,
        "sort": 0,
        "tagValuesQuery": "",
        "tags": [],
        "tagsQuery": "",
        "type": "query",
        "useTags": false
      },
      {
        "allValue": null,
        "current": {
          "selected": true,
          "text": [
            "All"
          ],
          "value": [
            "$__all"
          ]
        },
        "datasource": "ElasticsearchCOAP",
        "definition": "{\"find\": \"terms\", \"field\": \"Code.keyword\"}",
        "error": null,
        "hide": 0,
        "includeAll": true,
        "label": "Code",
        "multi": true,
        "name": "Code",
        "options": [
          {
            "selected": true,
            "text": "All",
            "value": "$__all"
          },
          {
            "selected": false,
            "text": "2.04_Charged",
            "value": "2.04_Charged"
          },
          {
            "selected": false,
            "text": "2.05_Content",
            "value": "2.05_Content"
          },
          {
            "selected": false,
            "text": "Empty_Message",
            "value": "Empty_Message"
          },
          {
            "selected": false,
            "text": "PUT",
            "value": "PUT"
          }
        ],
        "query": "{\"find\": \"terms\", \"field\": \"Code.keyword\"}",
        "refresh": 0,
        "regex": "",
        "skipUrlSync": false,
        "sort": 0,
        "tagValuesQuery": "",
        "tags": [],
        "tagsQuery": "",
        "type": "query",
        "useTags": false
      }
    ]
  },
  "time": {
    "from": "2017-06-09T06:08:45.000Z",
    "to": "2017-06-09T06:10:29.000Z"
  },
  "timepicker": {},
  "timezone": "",
  "title": "elastic coap v2",
  "uid": "KHd3sPaMz",
  "version": 10
}